snailjob/__init__.py
snailjob/args.py
snailjob/cfg.py
snailjob/ctx.py
snailjob/deco.py
snailjob/err.py
snailjob/exec.py
snailjob/log.py
snailjob/main.py
snailjob/rpc.py
snailjob/utils.py
snailjob/grpc/__init__.py
snailjob/grpc/_rpc.py
snailjob/grpc/_server.py
snailjob/grpc/snailjob_pb2.py
snailjob/grpc/snailjob_pb2_grpc.py
snailjob/http/__init__.py
snailjob/http/_rpc.py
snailjob/http/_server.py
snailjob/schemas/__init__.py
snailjob/schemas/_client.py
snailjob/schemas/_common.py
snailjob/schemas/_enums.py
snailjob/schemas/_server.py
snailjob_shell_executor/.env
snailjob_shell_executor/__init__.py
snailjob_shell_executor/args.py
snailjob_shell_executor/cfg.py
snailjob_shell_executor/ctx.py
snailjob_shell_executor/deco.py
snailjob_shell_executor/err.py
snailjob_shell_executor/exec.py
snailjob_shell_executor/log.py
snailjob_shell_executor/main.py
snailjob_shell_executor/rpc.py
snailjob_shell_executor/shell_executor.py
snailjob_shell_executor/utils.py
snailjob_shell_executor/grpc/__init__.py
snailjob_shell_executor/grpc/_rpc.py
snailjob_shell_executor/grpc/_server.py
snailjob_shell_executor/grpc/snailjob_pb2.py
snailjob_shell_executor/grpc/snailjob_pb2_grpc.py
snailjob_shell_executor/http/__init__.py
snailjob_shell_executor/http/_rpc.py
snailjob_shell_executor/http/_server.py
snailjob_shell_executor/schemas/__init__.py
snailjob_shell_executor/schemas/_client.py
snailjob_shell_executor/schemas/_common.py
snailjob_shell_executor/schemas/_enums.py
snailjob_shell_executor/schemas/_server.py
snailjob_shell_executor-0.0.5.dist-info/LICENSE
snailjob_shell_executor-0.0.5.dist-info/METADATA
snailjob_shell_executor-0.0.5.dist-info/WHEEL
snailjob_shell_executor-0.0.5.dist-info/entry_points.txt
snailjob_shell_executor-0.0.5.dist-info/top_level.txt
snailjob_shell_executor-0.0.5.dist-info/RECORD
