Metadata-Version: 2.1
Name: snailjob-shell-executor
Version: 0.0.5
Summary: SnailJob python客户端开发的Shell执行器
Home-page: https://github.com/rhinuxx/snail-job
Author: rhinux
Author-email: rhinux.x@gmail.com
Classifier: Programming Language :: Python :: 3
Classifier: License :: OSI Approved :: Apache Software License
Classifier: Operating System :: OS Independent
Requires-Python: >=3.6
License-File: LICENSE
Requires-Dist: pydantic==2.7.4
Requires-Dist: python-dotenv==1.0.1
Requires-Dist: aiohttp==3.10.9
Requires-Dist: protobuf==5.27.2
Requires-Dist: grpcio==1.66.2
